ab_core/token_validator/__init__.py
ab_core/token_validator/schema/__init__.py
ab_core/token_validator/schema/token_validator_type.py
ab_core/token_validator/schema/validated_token.py
ab_core/token_validator/token_validators/__init__.py
ab_core/token_validator/token_validators/base.py
ab_core/token_validator/token_validators/oidc.py
ab_core/token_validator/token_validators/template.py
ab_token_validator-0.1.8.dist-info/METADATA
ab_token_validator-0.1.8.dist-info/WHEEL
ab_token_validator-0.1.8.dist-info/licenses/LICENSE
ab_token_validator-0.1.8.dist-info/RECORD
