Metadata-Version: 2.4
Name: ab-token-validator
Version: 0.1.8
Author-email: Matthew Coulter <53892067+mattcoulter7@users.noreply.github.com>
License-File: LICENSE
Requires-Python: <4,>=3.12
Requires-Dist: ab-dependency<0.3.0,>=0.2.0
Requires-Dist: aiocache<0.13,>=0.12.3
Requires-Dist: fastapi<0.116,>=0.115.14
Requires-Dist: httpx<0.29,>=0.28.1
Requires-Dist: pydantic<3,>=2.11.7
Requires-Dist: python-jose[cryptography]<4,>=3.5.0
Requires-Dist: uuid7<0.2,>=0.1.0
Requires-Dist: yarl<2,>=1.20.1
